setup.py
autoprotocol_utilities/__init__.py
autoprotocol_utilities/bio_calculators.py
autoprotocol_utilities/container_helpers.py
autoprotocol_utilities/magnetic_helpers.py
autoprotocol_utilities/misc_helpers.py
autoprotocol_utilities/rectangle.py
autoprotocol_utilities/resource_helpers.py
autoprotocol_utilities/thermocycle_helpers.py
autoprotocol_utilities.egg-info/PKG-INFO
autoprotocol_utilities.egg-info/SOURCES.txt
autoprotocol_utilities.egg-info/dependency_links.txt
autoprotocol_utilities.egg-info/not-zip-safe
autoprotocol_utilities.egg-info/requires.txt
autoprotocol_utilities.egg-info/top_level.txt