Metadata-Version: 1.0
Name: autoprotocol-utilities
Version: 2.3.1
Summary: Helper methods to construct protocols using autoprotocol-python.
Home-page: https://github.com/transcriptic/autoprotocol-utilities
Author: All past and present Application Scientists
Author-email: vanessa@transcriptic.com
License: MIT
Platform: UNKNOWN
